{
  "tracks": [
    {
      "name": "The CIA",
      "artist": "Glass Beach",
      "image": "https://lastfm.freetls.fastly.net/i/u/174s/effe001744b5e4c8e06fe91a729db613.jpg",
      "nowPlaying": false,
      "timestamp": 1777039686
    },
    {
      "name": "MANGO",
      "artist": "Cheem",
      "image": "https://lastfm.freetls.fastly.net/i/u/174s/80cabadcf9351c045875ecf91a4a4a59.jpg",
      "nowPlaying": false,
      "timestamp": 1777039543
    },
    {
      "name": "The Shell Shack",
      "artist": "Billy Cobb",
      "image": "https://lastfm.freetls.fastly.net/i/u/174s/0f9a6ee554050220ea5a754d86da3f27.png",
      "nowPlaying": false,
      "timestamp": 1777039345
    },
    {
      "name": "Möbius Chicken Strip",
      "artist": "Origami Angel",
      "image": "https://lastfm.freetls.fastly.net/i/u/174s/54a96475b1090425554502e2227986ac.jpg",
      "nowPlaying": false,
      "timestamp": 1777039156
    },
    {
      "name": "Waiting",
      "artist": "Ultra Q",
      "image": "https://lastfm.freetls.fastly.net/i/u/174s/9a416f31d11c77481154985945364642.jpg",
      "nowPlaying": false,
      "timestamp": 1777038959
    }
  ]
}