{
  "tracks": [
    {
      "name": "Jesus on the Telephone",
      "artist": "Machinery of the Human Heart",
      "image": "https://lastfm.freetls.fastly.net/i/u/174s/3aed9cd00a67c3af26ad11834adfae94.jpg",
      "nowPlaying": false,
      "timestamp": 1781448983
    },
    {
      "name": "Second Sight Seer! S! (2222024 Edit)",
      "artist": "Will Wood",
      "image": "https://lastfm.freetls.fastly.net/i/u/174s/c8a34e3e3ede8b4c4f3f9359d6c583cf.png",
      "nowPlaying": false,
      "timestamp": 1781448775
    },
    {
      "name": "Know Me",
      "artist": "Sean Altman",
      "image": "https://lastfm.freetls.fastly.net/i/u/174s/e329d35e18310de07139ad2144f4b1f8.jpg",
      "nowPlaying": false,
      "timestamp": 1781448593
    },
    {
      "name": "The Queen of White Lies",
      "artist": "The Orion Experience",
      "image": "https://lastfm.freetls.fastly.net/i/u/174s/0d0ce0ad8eeb5715ef0802d1347a3bdf.jpg",
      "nowPlaying": false,
      "timestamp": 1781448404
    },
    {
      "name": "Amnesia Was Her Name",
      "artist": "Lemon Demon",
      "image": "https://lastfm.freetls.fastly.net/i/u/174s/ea7e9febbd7dd45bfc98c72d57a67f85.jpg",
      "nowPlaying": false,
      "timestamp": 1781448160
    }
  ]
}