{
  "tracks": [
    {
      "name": "yasu club",
      "artist": "Lucy Bedroque",
      "image": "https://lastfm.freetls.fastly.net/i/u/174s/1cac9089b965e442b94df9d358c8008c.jpg",
      "nowPlaying": false,
      "timestamp": 1775635060
    },
    {
      "name": "ᏋᏒᎧᎶᏋ ᏝᎧᏉᏋ ᎮᎧᏖᎥᎧᏁ",
      "artist": "Junshi",
      "image": "https://lastfm.freetls.fastly.net/i/u/174s/31d7f2b918c806a249c6837198498873.png",
      "nowPlaying": false,
      "timestamp": 1775634940
    },
    {
      "name": "Do It (Yves Remix)",
      "artist": "underscores",
      "image": "https://lastfm.freetls.fastly.net/i/u/174s/fb5a9db0f286b4ca638783d91437b78d.png",
      "nowPlaying": false,
      "timestamp": 1775634747
    },
    {
      "name": "ᏉᏬᏝᏁᏋᏒᏗᏰᏝᏋ, ᏇᎥᏝᏝ ᎩᎧᏬ ᏕᏖᎥᏝᏝ ᏝᎧᏉᏋ ᎷᏋ?",
      "artist": "sayako",
      "image": "https://lastfm.freetls.fastly.net/i/u/174s/a61eb5d41e4ddbbdc3881a1ef1cf495b.jpg",
      "nowPlaying": false,
      "timestamp": 1775634593
    },
    {
      "name": "Cream Soda",
      "artist": "venturing",
      "image": "https://lastfm.freetls.fastly.net/i/u/174s/6db51943e908f51fb551290e335e53be.jpg",
      "nowPlaying": false,
      "timestamp": 1775634500
    }
  ]
}